gym_breakout_pygame/__init__.py
gym_breakout_pygame/__main__.py
gym_breakout_pygame/breakout_env.py
gym_breakout_pygame/utils.py
gym_breakout_pygame/wrappers/__init__.py
gym_breakout_pygame/wrappers/dict_space.py
gym_breakout_pygame/wrappers/normal_space.py
gym_breakout_pygame/wrappers/skipper.py
gym_breakout_pygame-0.2.0.dist-info/LICENSE
gym_breakout_pygame-0.2.0.dist-info/WHEEL
gym_breakout_pygame-0.2.0.dist-info/METADATA
gym_breakout_pygame-0.2.0.dist-info/RECORD
