Metadata-Version: 2.1
Name: gym-breakout-pygame
Version: 0.2.0
Summary: Gym Breakout environment using Pygame.
Home-page: https://whitemech.github.io/gym-breakout-pygame
License: GPL-3.0-or-later
Keywords: environment,agent,rl,openaigym,openai-gym,gym,breakout
Author: Marco Favorito
Author-email: favorito@diag.uniroma1.it
Requires-Python: >=3.8,<3.11
Classifier: Development Status :: 2 - Pre-Alpha
Classifier: Intended Audience :: Developers
Classifier: License :: OSI Approved :: GNU General Public License v3 or later (GPLv3+)
Classifier: License :: OSI Approved :: MIT License
Classifier: Natural Language :: English
Classifier: Programming Language :: Python :: 3
Classifier: Programming Language :: Python :: 3.8
Classifier: Programming Language :: Python :: 3.9
Classifier: Programming Language :: Python :: 3.10
Classifier: Programming Language :: Python :: 3
Classifier: Programming Language :: Python :: 3.10
Classifier: Programming Language :: Python :: 3.8
Classifier: Programming Language :: Python :: 3.9
Classifier: Topic :: Games/Entertainment :: Arcade
Requires-Dist: gym (>=0.26.2,<0.27.0)
Requires-Dist: numpy (>=1.23.3,<2.0.0)
Requires-Dist: pygame (>=2.1.2,<3.0.0)
Project-URL: Bug Tracker, https://github.com/whitemech/gym-breakout-pygame/issues
Project-URL: Documentation, https://whitemech.github.io/gym-breakout-pygame
Project-URL: Pull Requests, https://github.com/whitemech/gym-breakout-pygame/pulls
Project-URL: Repository, https://github.com/whitemech/gym-breakout-pygame.git
